genBarcode/__init__.py
genBarcode/__main__.py
genBarcode/classes/__init__.py
genBarcode/classes/CustomExceptions.py
genBarcode/classes/ReturnCodes.py
LICENSE
genbarcode-1.0.1.dist-info/entry_points.txt
genbarcode-1.0.1.dist-info/LICENSE
genbarcode-1.0.1.dist-info/WHEEL
genbarcode-1.0.1.dist-info/METADATA
genbarcode-1.0.1.dist-info/RECORD
